py_ravif-0.0.1.dist-info/METADATA
py_ravif-0.0.1.dist-info/WHEEL
py_ravif-0.0.1.dist-info/license_files/LICENSE
py_ravif/__init__.py
py_ravif/py_ravif.cpython-310-darwin.so
py_ravif-0.0.1.dist-info/RECORD
