Metadata-Version: 2.1
Name: py-ravif
Version: 0.0.1
Classifier: Programming Language :: Rust
Classifier: Programming Language :: Python :: Implementation :: CPython
Classifier: Programming Language :: Python :: Implementation :: PyPy
License-File: LICENSE
Summary: Python bindings for avif image encoding library ravif.
License: BSD-3-Clause
Requires-Python: >=3.6
